{
  "https://esf1.fang.com/": "北京",
  "https://sh.esf.fang.com/": "上海",
  "https://tj.esf.fang.com/": "天津",
  "https://changshou.esf.fang.com": "长寿",
  "https://jiangjin.esf.fang.com": "江津",
  "https://yongchuan.esf.fang.com": "永川",
  "https://cq.esf.fang.com": "重庆",
  "https://bishan.esf.fang.com": "璧山",
  "https://dazu.esf.fang.com": "大足",
  "https://dianjiang.esf.fang.com": "垫江",
  "https://fengjie.esf.fang.com": "奉节",
  "https://kaixian.esf.fang.com": "开县",
  "https://liangping.esf.fang.com": "梁平",
  "https://rongchang.esf.fang.com": "荣昌",
  "https://shizhu.esf.fang.com": "石柱",
  "https://tongnan.esf.fang.com": "潼南",
  "https://wulong.esf.fang.com": "武隆",
  "https://wushan.esf.fang.com": "巫山",
  "https://yunyang.esf.fang.com": "云阳",
  "https://zhongxian.esf.fang.com": "忠县",
  "https://tongliang.esf.fang.com": "铜梁",
  "https://fengdu.esf.fang.com": "丰都",
  "https://xingtai.esf.fang.com": "邢台",
  "https://zhangjiakou.esf.fang.com": "张家口",
  "https://chengde.esf.fang.com": "承德",
  "https://cangzhou.esf.fang.com": "沧州",
  "https://zhangbei.esf.fang.com": "张北",
  "https://zunhua.esf.fang.com": "遵化",
  "https://qianan.esf.fang.com": "迁安",
  "https://hd.esf.fang.com": "邯郸",
  "https://bd.esf.fang.com": "保定",
  "https://hs.esf.fang.com": "衡水",
  "https://lf.esf.fang.com": "廊坊",
  "https://qhd.esf.fang.com": "秦皇岛",
  "https://sjz.esf.fang.com": "石家庄",
  "https://ts.esf.fang.com": "唐山",
  "https://dingzhou.esf.fang.com": "定州",
  "https://xinji.esf.fang.com": "辛集",
  "https://luanxian.esf.fang.com": "滦县",
  "https://yutian.esf.fang.com": "玉田",
  "https://hbjz.esf.fang.com": "晋州",
  "https://luannan.esf.fang.com": "滦南",
  "https://gaobeidian.esf.fang.com": "高碑店",
  "https://hblt.esf.fang.com": "乐亭",
  "https://qianxi.esf.fang.com": "迁西",
  "https://hbql.esf.fang.com": "青龙",
  "https://hbwj.esf.fang.com": "无极",
  "https://hbzx.esf.fang.com": "赵县",
  "https://hbys.esf.fang.com": "元氏",
  "https://wenan.esf.fang.com": "文安",
  "https://xinle.esf.fang.com": "新乐",
  "https://hbbz.esf.fang.com": "霸州",
  "https://changli.esf.fang.com": "昌黎",
  "https://hbps.esf.fang.com": "平山",
  "https://wuan.esf.fang.com": "武安",
  "https://renqiu.esf.fang.com": "任丘",
  "https://jz.esf.fang.com": "冀州",
  "https://hbsh.esf.fang.com": "三河",
  "https://hbsz.esf.fang.com": "深州",
  "https://dingxing.esf.fang.com": "定兴",
  "https://datong.esf.fang.com": "大同",
  "https://yangquan.esf.fang.com": "阳泉",
  "https://changzhi.esf.fang.com": "长治",
  "https://shuozhou.esf.fang.com": "朔州",
  "https://jinzhong.esf.fang.com": "晋中",
  "https://xinzhou.esf.fang.com": "忻州",
  "https://linfen.esf.fang.com": "临汾",
  "https://lvliang.esf.fang.com": "吕梁",
  "https://yuncheng.esf.fang.com": "运城",
  "https://jc.esf.fang.com": "晋城",
  "https://sxly.esf.fang.com": "临猗",
  "https://taiyuan.esf.fang.com": "太原",
  "https://qingxu.esf.fang.com": "清徐",
  "https://yangqu.esf.fang.com": "阳曲",
  "https://huairen.esf.fang.com": "怀仁",
  "https://chifeng.esf.fang.com": "赤峰",
  "https://wlcb.esf.fang.com": "乌兰察布",
  "https://tl.esf.fang.com": "通辽",
  "https://alsm.esf.fang.com": "阿拉善盟",
  "https://erds.esf.fang.com": "鄂尔多斯",
  "https://bt.esf.fang.com": "包头",
  "https://wuhai.esf.fang.com": "乌海",
  "https://xlglm.esf.fang.com": "锡林郭勒盟",
  "https://xam.esf.fang.com": "兴安盟",
  "https://byne.esf.fang.com": "巴彦淖尔",
  "https://hailaer.esf.fang.com": "海拉尔",
  "https://hlbe.esf.fang.com": "呼伦贝尔",
  "https://nm.esf.fang.com": "呼和浩特",
  "https://xilinhaote.esf.fang.com": "锡林浩特",
  "https://fushun.esf.fang.com": "抚顺",
  "https://benxi.esf.fang.com": "本溪",
  "https://dandong.esf.fang.com": "丹东",
  "https://jinzhou.esf.fang.com": "锦州",
  "https://fuxin.esf.fang.com": "阜新",
  "https://liaoyang.esf.fang.com": "辽阳",
  "https://panjin.esf.fang.com": "盘锦",
  "https://tieling.esf.fang.com": "铁岭",
  "https://chaoyang.esf.fang.com": "朝阳",
  "https://huludao.esf.fang.com": "葫芦岛",
  "https://yk.esf.fang.com": "营口",
  "https://lnzh.esf.fang.com": "庄河",
  "https://pulandian.esf.fang.com": "普兰店",
  "https://anshan.esf.fang.com": "鞍山",
  "https://dl.esf.fang.com": "大连",
  "https://sy.esf.fang.com": "沈阳",
  "https://wafangdian.esf.fang.com": "瓦房店",
  "https://donggang.esf.fang.com": "东港",
  "https://fengcheng.esf.fang.com": "凤城",
  "https://xinmin.esf.fang.com": "新民",
  "https://liaozhong.esf.fang.com": "辽中",
  "https://faku.esf.fang.com": "法库",
  "https://kangping.esf.fang.com": "康平",
  "https://haicheng.esf.fang.com": "海城",
  "https://lnta.esf.fang.com": "台安",
  "https://siping.esf.fang.com": "四平",
  "https://liaoyuan.esf.fang.com": "辽源",
  "https://tonghua.esf.fang.com": "通化",
  "https://baishan.esf.fang.com": "白山",
  "https://songyuan.esf.fang.com": "松原",
  "https://baicheng.esf.fang.com": "白城",
  "https://yanbian.esf.fang.com": "延边",
  "https://changchun.esf.fang.com": "长春",
  "https://jl.esf.fang.com": "吉林",
  "https://nongan.esf.fang.com": "农安",
  "https://dehui.esf.fang.com": "德惠",
  "https://jlys.esf.fang.com": "榆树",
  "https://gongzhuling.esf.fang.com": "公主岭",
  "https://huadian.esf.fang.com": "桦甸",
  "https://qiqihaer.esf.fang.com": "齐齐哈尔",
  "https://jixi.esf.fang.com": "鸡西",
  "https://hegang.esf.fang.com": "鹤岗",
  "https://shuangyashan.esf.fang.com": "双鸭山",
  "https://hljyichun.esf.fang.com": "伊春",
  "https://jiamusi.esf.fang.com": "佳木斯",
  "https://qitaihe.esf.fang.com": "七台河",
  "https://mudanjiang.esf.fang.com": "牡丹江",
  "https://heihe.esf.fang.com": "黑河",
  "https://suihua.esf.fang.com": "绥化",
  "https://dxal.esf.fang.com": "大兴安岭",
  "https://daqing.esf.fang.com": "大庆",
  "https://hrb.esf.fang.com": "哈尔滨",
  "https://zhaodong.esf.fang.com": "肇东",
  "https://binxian.esf.fang.com": "宾县",
  "https://anda.esf.fang.com": "安达",
  "https://bayan.esf.fang.com": "巴彦",
  "https://shangzhi.esf.fang.com": "尚志",
  "https://wuchang.esf.fang.com": "五常",
  "https://yilan.esf.fang.com": "依兰",
  "https://zhaoyuan.esf.fang.com": "肇源",
  "https://zhaozhou.esf.fang.com": "肇州",
  "https://hailin.esf.fang.com": "海林",
  "https://yixing.esf.fang.com": "宜兴",
  "https://shuyang.esf.fang.com": "沭阳",
  "https://zjg.esf.fang.com": "张家港",
  "https://sq.esf.fang.com": "宿迁",
  "https://tc.esf.fang.com": "太仓",
  "https://pizhou.esf.fang.com": "邳州",
  "https://xinghua.esf.fang.com": "兴化",
  "https://rugao.esf.fang.com": "如皋",
  "https://liyang.esf.fang.com": "溧阳",
  "https://taixing.esf.fang.com": "泰兴",
  "https://dongtai.esf.fang.com": "东台",
  "https://qidong.esf.fang.com": "启东",
  "https://jiangdu.esf.fang.com": "江都",
  "https://haimen.esf.fang.com": "海门",
  "https://xinyi.esf.fang.com": "新沂",
  "https://gaoyou.esf.fang.com": "高邮",
  "https://jingjiang.esf.fang.com": "靖江",
  "https://changshu.esf.fang.com": "常熟",
  "https://cz.esf.fang.com": "常州",
  "https://huaian.esf.fang.com": "淮安",
  "https://jy.esf.fang.com": "江阴",
  "https://ks.esf.fang.com": "昆山",
  "https://lyg.esf.fang.com": "连云港",
  "https://nanjing.esf.fang.com": "南京",
  "https://nt.esf.fang.com": "南通",
  "https://suzhou.esf.fang.com": "苏州",
  "https://taizhou.esf.fang.com": "泰州",
  "https://wuxi.esf.fang.com": "无锡",
  "https://wj.esf.fang.com": "吴江",
  "https://xz.esf.fang.com": "徐州",
  "https://yancheng.esf.fang.com": "盐城",
  "https://yz.esf.fang.com": "扬州",
  "https://zhenjiang.esf.fang.com": "镇江",
  "https://rudong.esf.fang.com": "如东",
  "https://yizheng.esf.fang.com": "仪征",
  "https://jintan.esf.fang.com": "金坛",
  "https://jssn.esf.fang.com": "睢宁",
  "https://jsfx.esf.fang.com": "丰县",
  "https://peixian.esf.fang.com": "沛县",
  "https://baoying.esf.fang.com": "宝应",
  "https://jr.esf.fang.com": "句容",
  "https://funing.esf.fang.com": "阜宁",
  "https://njgc.esf.fang.com": "高淳",
  "https://jiangyan.esf.fang.com": "姜堰",
  "https://quanshan.esf.fang.com": "泉山",
  "https://tongshan.esf.fang.com": "铜山",
  "https://ksys.esf.fang.com": "玉山",
  "https://haian.esf.fang.com": "海安",
  "https://jinhu.esf.fang.com": "金湖",
  "https://donghai.esf.fang.com": "东海",
  "https://xuyi.esf.fang.com": "盱眙",
  "https://quzhou.esf.fang.com": "衢州",
  "https://changxing.esf.fang.com": "长兴",
  "https://deqing.esf.fang.com": "德清",
  "https://tz.esf.fang.com": "台州",
  "https://ruian.esf.fang.com": "瑞安",
  "https://ls.esf.fang.com": "丽水",
  "https://yueqing.esf.fang.com": "乐清",
  "https://haining.esf.fang.com": "海宁",
  "https://wenling.esf.fang.com": "温岭",
  "https://linhai.esf.fang.com": "临海",
  "https://zhuji.esf.fang.com": "诸暨",
  "https://cixi.esf.fang.com": "慈溪",
  "https://yuyao.esf.fang.com": "余姚",
  "https://tongxiang.esf.fang.com": "桐乡",
  "https://shangyu.esf.fang.com": "上虞",
  "https://pinghu.esf.fang.com": "平湖",
  "https://zjfy.esf.fang.com": "富阳",
  "https://ninghai.esf.fang.com": "宁海",
  "https://fenghua.esf.fang.com": "奉化",
  "https://hz.esf.fang.com": "杭州",
  "https://huzhou.esf.fang.com": "湖州",
  "https://jx.esf.fang.com": "嘉兴",
  "https://jh.esf.fang.com": "金华",
  "https://nb.esf.fang.com": "宁波",
  "https://shaoxing.esf.fang.com": "绍兴",
  "https://wz.esf.fang.com": "温州",
  "https://zhoushan.esf.fang.com": "舟山",
  "https://linan.esf.fang.com": "临安",
  "https://jiande.esf.fang.com": "建德",
  "https://zjtl.esf.fang.com": "桐庐",
  "https://zjxs.esf.fang.com": "象山",
  "https://yuhuan.esf.fang.com": "玉环",
  "https://chunan.esf.fang.com": "淳安",
  "https://zhenhai.esf.fang.com": "镇海",
  "https://aj.esf.fang.com": "安吉",
  "https://haiyan.esf.fang.com": "海盐",
  "https://huaibei.esf.fang.com": "淮北",
  "https://tongling.esf.fang.com": "铜陵",
  "https://anqing.esf.fang.com": "安庆",
  "https://huangshan.esf.fang.com": "黄山",
  "https://chuzhou.esf.fang.com": "滁州",
  "https://fuyang.esf.fang.com": "阜阳",
  "https://ahsuzhou.esf.fang.com": "宿州",
  "https://chaohu.esf.fang.com": "巢湖",
  "https://luan.esf.fang.com": "六安",
  "https://bozhou.esf.fang.com": "亳州",
  "https://chizhou.esf.fang.com": "池州",
  "https://xuancheng.esf.fang.com": "宣城",
  "https://huoqiu.esf.fang.com": "霍邱",
  "https://tongcheng.esf.fang.com": "桐城",
  "https://bengbu.esf.fang.com": "蚌埠",
  "https://hf.esf.fang.com": "合肥",
  "https://huainan.esf.fang.com": "淮南",
  "https://mas.esf.fang.com": "马鞍山",
  "https://wuhu.esf.fang.com": "芜湖",
  "https://feixi.esf.fang.com": "肥西",
  "https://lujiang.esf.fang.com": "庐江",
  "https://feidong.esf.fang.com": "肥东",
  "https://dangtu.esf.fang.com": "当涂",
  "https://ahcf.esf.fang.com": "长丰",
  "https://guzhen.esf.fang.com": "固镇",
  "https://huaiyuan.esf.fang.com": "怀远",
  "https://wuhe.esf.fang.com": "五河",
  "https://fanchang.esf.fang.com": "繁昌",
  "https://sanming.esf.fang.com": "三明",
  "https://nanping.esf.fang.com": "南平",
  "https://longyan.esf.fang.com": "龙岩",
  "https://ningde.esf.fang.com": "宁德",
  "https://fq.esf.fang.com": "福清",
  "https://pingtan.esf.fang.com": "平潭",
  "https://nanan.esf.fang.com": "南安",
  "https://longhai.esf.fang.com": "龙海",
  "https://huian.esf.fang.com": "惠安",
  "https://changle.esf.fang.com": "长乐",
  "https://shishi.esf.fang.com": "石狮",
  "https://fz.esf.fang.com": "福州",
  "https://putian.esf.fang.com": "莆田",
  "https://qz.esf.fang.com": "泉州",
  "https://xm.esf.fang.com": "厦门",
  "https://zhangzhou.esf.fang.com": "漳州",
  "https://fjax.esf.fang.com": "安溪",
  "https://lianjiang.esf.fang.com": "连江",
  "https://yongchun.esf.fang.com": "永春",
  "https://luoyuan.esf.fang.com": "罗源",
  "https://minqing.esf.fang.com": "闽清",
  "https://quangang.esf.fang.com": "泉港",
  "https://yongtai.esf.fang.com": "永泰",
  "https://fuan.esf.fang.com": "福安",
  "https://dh.esf.fang.com": "德化",
  "https://ya.esf.fang.com": "永安",
  "https://jingdezhen.esf.fang.com": "景德镇",
  "https://pingxiang.esf.fang.com": "萍乡",
  "https://xinyu.esf.fang.com": "新余",
  "https://yingtan.esf.fang.com": "鹰潭",
  "https://jian.esf.fang.com": "吉安",
  "https://yichun.esf.fang.com": "宜春",
  "https://jxfuzhou.esf.fang.com": "抚州",
  "https://shangrao.esf.fang.com": "上饶",
  "https://ganzhou.esf.fang.com": "赣州",
  "https://jiujiang.esf.fang.com": "九江",
  "https://nc.esf.fang.com": "南昌",
  "https://jinxian.esf.fang.com": "进贤",
  "https://xinjian.esf.fang.com": "新建",
  "https://ruijin.esf.fang.com": "瑞金",
  "https://jxfc.esf.fang.com": "丰城",
  "https://jxja.esf.fang.com": "靖安",
  "https://zaozhuang.esf.fang.com": "枣庄",
  "https://jining.esf.fang.com": "济宁",
  "https://taian.esf.fang.com": "泰安",
  "https://laiwu.esf.fang.com": "莱芜",
  "https://dz.esf.fang.com": "德州",
  "https://rz.esf.fang.com": "日照",
  "https://heze.esf.fang.com": "菏泽",
  "https://lc.esf.fang.com": "聊城",
  "https://linyi.esf.fang.com": "临沂",
  "https://dy.esf.fang.com": "东营",
  "https://zhangqiu.esf.fang.com": "章丘",
  "https://zy.esf.fang.com": "招远",
  "https://tengzhou.esf.fang.com": "滕州",
  "https://pingdu.esf.fang.com": "平度",
  "https://xintai.esf.fang.com": "新泰",
  "https://zoucheng.esf.fang.com": "邹城",
  "https://feicheng.esf.fang.com": "肥城",
  "https://laizhou.esf.fang.com": "莱州",
  "https://zouping.esf.fang.com": "邹平",
  "https://jiaonan.esf.fang.com": "胶南",
  "https://longkou.esf.fang.com": "龙口",
  "https://zb.esf.fang.com": "淄博",
  "https://binzhou.esf.fang.com": "滨州",
  "https://jn.esf.fang.com": "济南",
  "https://qd.esf.fang.com": "青岛",
  "https://weihai.esf.fang.com": "威海",
  "https://wf.esf.fang.com": "潍坊",
  "https://yt.esf.fang.com": "烟台",
  "https://jimo.esf.fang.com": "即墨",
  "https://laixi.esf.fang.com": "莱西",
  "https://guangrao.esf.fang.com": "广饶",
  "https://penglai.esf.fang.com": "蓬莱",
  "https://sdjy.esf.fang.com": "济阳",
  "https://sdsh.esf.fang.com": "商河",
  "https://laiyang.esf.fang.com": "莱阳",
  "https://sdpy.esf.fang.com": "平阴",
  "https://linqing.esf.fang.com": "临清",
  "https://qixia.esf.fang.com": "栖霞",
  "https://haiyang.esf.fang.com": "海阳",
  "https://ytcd.esf.fang.com": "长岛",
  "https://jncq.esf.fang.com": "长清",
  "https://jiaozhou.esf.fang.com": "胶州",
  "https://qihe.esf.fang.com": "齐河",
  "https://qingyun.esf.fang.com": "庆云",
  "https://kaifeng.esf.fang.com": "开封",
  "https://pingdingshan.esf.fang.com": "平顶山",
  "https://anyang.esf.fang.com": "安阳",
  "https://hebi.esf.fang.com": "鹤壁",
  "https://jiaozuo.esf.fang.com": "焦作",
  "https://puyang.esf.fang.com": "濮阳",
  "https://xuchang.esf.fang.com": "许昌",
  "https://luohe.esf.fang.com": "漯河",
  "https://sanmenxia.esf.fang.com": "三门峡",
  "https://nanyang.esf.fang.com": "南阳",
  "https://shangqiu.esf.fang.com": "商丘",
  "https://xinyang.esf.fang.com": "信阳",
  "https://zhoukou.esf.fang.com": "周口",
  "https://zhumadian.esf.fang.com": "驻马店",
  "https://xx.esf.fang.com": "新乡",
  "https://hnyz.esf.fang.com": "禹州",
  "https://changge.esf.fang.com": "长葛",
  "https://yanling.esf.fang.com": "鄢陵",
  "https://gongyi.esf.fang.com": "巩义",
  "https://jiyuan.esf.fang.com": "济源",
  "https://ly.esf.fang.com": "洛阳",
  "https://zz.esf.fang.com": "郑州",
  "https://xinzheng.esf.fang.com": "新郑",
  "https://xingyang.esf.fang.com": "荥阳",
  "https://yichuan.esf.fang.com": "伊川",
  "https://yanshi.esf.fang.com": "偃师",
  "https://zhongmou.esf.fang.com": "中牟",
  "https://dengfeng.esf.fang.com": "登封",
  "https://hnxa.esf.fang.com": "新安",
  "https://hnyy.esf.fang.com": "宜阳",
  "https://xinmi.esf.fang.com": "新密",
  "https://songxian.esf.fang.com": "嵩县",
  "https://luoning.esf.fang.com": "洛宁",
  "https://mengjin.esf.fang.com": "孟津",
  "https://ruyang.esf.fang.com": "汝阳",
  "https://dengzhou.esf.fang.com": "邓州",
  "https://lankao.esf.fang.com": "兰考",
  "https://ruzhou.esf.fang.com": "汝州",
  "https://luanchuan.esf.fang.com": "栾川",
  "https://yongcheng.esf.fang.com": "永城",
  "https://wg.esf.fang.com": "舞钢",
  "https://shiyan.esf.fang.com": "十堰",
  "https://ezhou.esf.fang.com": "鄂州",
  "https://jingmen.esf.fang.com": "荆门",
  "https://xiaogan.esf.fang.com": "孝感",
  "https://jingzhou.esf.fang.com": "荆州",
  "https://huanggang.esf.fang.com": "黄冈",
  "https://xianning.esf.fang.com": "咸宁",
  "https://suizhou.esf.fang.com": "随州",
  "https://enshi.esf.fang.com": "恩施",
  "https://xiantao.esf.fang.com": "仙桃",
  "https://shennongjia.esf.fang.com": "神农架",
  "https://tianmen.esf.fang.com": "天门",
  "https://qj.esf.fang.com": "潜江",
  "https://huangshi.esf.fang.com": "黄石",
  "https://wuhan.esf.fang.com": "武汉",
  "https://xiangyang.esf.fang.com": "襄阳",
  "https://yc.esf.fang.com": "宜昌",
  "https://dangyang.esf.fang.com": "当阳",
  "https://yidu.esf.fang.com": "宜都",
  "https://zhijiang.esf.fang.com": "枝江",
  "https://whhn.esf.fang.com": "汉南",
  "https://hbjs.esf.fang.com": "京山",
  "https://zhongxiang.esf.fang.com": "钟祥",
  "https://lhk.esf.fang.com": "老河口",
  "https://hbyc.esf.fang.com": "宜城",
  "https://hbzy.esf.fang.com": "枣阳",
  "https://hanchuan.esf.fang.com": "汉川",
  "https://shaoyang.esf.fang.com": "邵阳",
  "https://zhangjiajie.esf.fang.com": "张家界",
  "https://yiyang.esf.fang.com": "益阳",
  "https://chenzhou.esf.fang.com": "郴州",
  "https://yongzhou.esf.fang.com": "永州",
  "https://huaihua.esf.fang.com": "怀化",
  "https://loudi.esf.fang.com": "娄底",
  "https://xiangxi.esf.fang.com": "湘西",
  "https://cs.esf.fang.com": "长沙",
  "https://changde.esf.fang.com": "常德",
  "https://hengyang.esf.fang.com": "衡阳",
  "https://xt.esf.fang.com": "湘潭",
  "https://yueyang.esf.fang.com": "岳阳",
  "https://zhuzhou.esf.fang.com": "株洲",
  "https://liuyang.esf.fang.com": "浏阳",
  "https://ningxiang.esf.fang.com": "宁乡",
  "https://liling.esf.fang.com": "醴陵",
  "https://xiangxiang.esf.fang.com": "湘乡",
  "https://youxian.esf.fang.com": "攸县",
  "https://cswc.esf.fang.com": "望城",
  "https://leiyang.esf.fang.com": "耒阳",
  "https://cn.esf.fang.com": "常宁",
  "https://ss.esf.fang.com": "韶山",
  "https://shaoguan.esf.fang.com": "韶关",
  "https://shanwei.esf.fang.com": "汕尾",
  "https://heyuan.esf.fang.com": "河源",
  "https://chaozhou.esf.fang.com": "潮州",
  "https://jieyang.esf.fang.com": "揭阳",
  "https://yunfu.esf.fang.com": "云浮",
  "https://shunde.esf.fang.com": "顺德",
  "https://yangchun.esf.fang.com": "阳春",
  "https://kaiping.esf.fang.com": "开平",
  "https://dg.esf.fang.com": "东莞",
  "https://fs.esf.fang.com": "佛山",
  "https://gz.esf.fang.com": "广州",
  "https://huizhou.esf.fang.com": "惠州",
  "https://jm.esf.fang.com": "江门",
  "https://maoming.esf.fang.com": "茂名",
  "https://meizhou.esf.fang.com": "梅州",
  "https://qingyuan.esf.fang.com": "清远",
  "https://st.esf.fang.com": "汕头",
  "https://sz.esf.fang.com": "深圳",
  "https://yangjiang.esf.fang.com": "阳江",
  "https://zj.esf.fang.com": "湛江",
  "https://zhaoqing.esf.fang.com": "肇庆",
  "https://zs.esf.fang.com": "中山",
  "https://zh.esf.fang.com": "珠海",
  "https://taishan.esf.fang.com": "台山",
  "https://enping.esf.fang.com": "恩平",
  "https://huidong.esf.fang.com": "惠东",
  "https://gdlm.esf.fang.com": "龙门",
  "https://boluo.esf.fang.com": "博罗",
  "https://heshan.esf.fang.com": "鹤山",
  "https://puning.esf.fang.com": "普宁",
  "https://xf.esf.fang.com": "新丰",
  "https://guangde.esf.fang.com": "广德",
  "https://wuzhou.esf.fang.com": "梧州",
  "https://qinzhou.esf.fang.com": "钦州",
  "https://baise.esf.fang.com": "百色",
  "https://hezhou.esf.fang.com": "贺州",
  "https://hechi.esf.fang.com": "河池",
  "https://laibin.esf.fang.com": "来宾",
  "https://chongzuo.esf.fang.com": "崇左",
  "https://yl.esf.fang.com": "玉林",
  "https://bh.esf.fang.com": "北海",
  "https://fangchenggang.esf.fang.com": "防城港",
  "https://guigang.esf.fang.com": "贵港",
  "https://guilin.esf.fang.com": "桂林",
  "https://liuzhou.esf.fang.com": "柳州",
  "https://nn.esf.fang.com": "南宁",
  "https://gxby.esf.fang.com": "宾阳",
  "https://hengxian.esf.fang.com": "横县",
  "https://yongning.esf.fang.com": "邕宁",
  "https://zigong.esf.fang.com": "自贡",
  "https://panzhihua.esf.fang.com": "攀枝花",
  "https://guangyuan.esf.fang.com": "广元",
  "https://yibin.esf.fang.com": "宜宾",
  "https://guangan.esf.fang.com": "广安",
  "https://dazhou.esf.fang.com": "达州",
  "https://yaan.esf.fang.com": "雅安",
  "https://bazhong.esf.fang.com": "巴中",
  "https://ziyang.esf.fang.com": "资阳",
  "https://liangshan.esf.fang.com": "凉山",
  "https://abazhou.esf.fang.com": "阿坝州",
  "https://fuling.esf.fang.com": "涪陵",
  "https://qianjiang.esf.fang.com": "黔江",
  "https://wanzhou.esf.fang.com": "万州",
  "https://qijiang.esf.fang.com": "綦江",
  "https://hechuan.esf.fang.com": "合川",
  "https://ganzi.esf.fang.com": "甘孜",
  "https://cd.esf.fang.com": "成都",
  "https://deyang.esf.fang.com": "德阳",
  "https://leshan.esf.fang.com": "乐山",
  "https://luzhou.esf.fang.com": "泸州",
  "https://meishan.esf.fang.com": "眉山",
  "https://mianyang.esf.fang.com": "绵阳",
  "https://neijiang.esf.fang.com": "内江",
  "https://nanchong.esf.fang.com": "南充",
  "https://suining.esf.fang.com": "遂宁",
  "https://pengzhou.esf.fang.com": "彭州",
  "https://scjt.esf.fang.com": "金堂",
  "https://qionglai.esf.fang.com": "邛崃",
  "https://chongzhou.esf.fang.com": "崇州",
  "https://dayi.esf.fang.com": "大邑",
  "https://jianyang.esf.fang.com": "简阳",
  "https://dujiangyan.esf.fang.com": "都江堰",
  "https://xinjin.esf.fang.com": "新津",
  "https://emeishan.esf.fang.com": "峨眉山",
  "https://lps.esf.fang.com": "六盘水",
  "https://zunyi.esf.fang.com": "遵义",
  "https://anshun.esf.fang.com": "安顺",
  "https://tongren.esf.fang.com": "铜仁",
  "https://qianxinan.esf.fang.com": "黔西南",
  "https://bijie.esf.fang.com": "毕节",
  "https://qdn.esf.fang.com": "黔东南",
  "https://qiannan.esf.fang.com": "黔南",
  "https://gy.esf.fang.com": "贵阳",
  "https://kaiyang.esf.fang.com": "开阳",
  "https://xiuwen.esf.fang.com": "修文",
  "https://qingzhen.esf.fang.com": "清镇",
  "https://yuxi.esf.fang.com": "玉溪",
  "https://baoshan.esf.fang.com": "保山",
  "https://zhaotong.esf.fang.com": "昭通",
  "https://puer.esf.fang.com": "普洱",
  "https://lincang.esf.fang.com": "临沧",
  "https://chuxiong.esf.fang.com": "楚雄",
  "https://honghe.esf.fang.com": "红河",
  "https://wenshan.esf.fang.com": "文山",
  "https://xishuangbanna.esf.fang.com": "西双版纳",
  "https://dali.esf.fang.com": "大理",
  "https://dehong.esf.fang.com": "德宏",
  "https://diqing.esf.fang.com": "迪庆",
  "https://nujiang.esf.fang.com": "怒江",
  "https://km.esf.fang.com": "昆明",
  "https://lijiang.esf.fang.com": "丽江",
  "https://qujing.esf.fang.com": "曲靖",
  "https://anning.esf.fang.com": "安宁",
  "https://ynyl.esf.fang.com": "宜良",
  "https://sansha.esf.fang.com": "三沙",
  "https://wuzhishan.esf.fang.com": "五指山",
  "https://hn.esf.fang.com": "海南",
  "https://sanya.esf.fang.com": "三亚",
  "https://dongfang.esf.fang.com": "东方",
  "https://danzhou.esf.fang.com": "儋州",
  "https://wanning.esf.fang.com": "万宁",
  "https://wenchang.esf.fang.com": "文昌",
  "https://qionghai.esf.fang.com": "琼海",
  "https://tongchuan.esf.fang.com": "铜川",
  "https://weinan.esf.fang.com": "渭南",
  "https://yanan.esf.fang.com": "延安",
  "https://hanzhong.esf.fang.com": "汉中",
  "https://sxyulin.esf.fang.com": "榆林",
  "https://ankang.esf.fang.com": "安康",
  "https://shangluo.esf.fang.com": "商洛",
  "https://baoji.esf.fang.com": "宝鸡",
  "https://xian.esf.fang.com": "西安",
  "https://xianyang.esf.fang.com": "咸阳",
  "https://lantian.esf.fang.com": "蓝田",
  "https://huxian.esf.fang.com": "户县",
  "https://zhouzhi.esf.fang.com": "周至",
  "https://gaoling.esf.fang.com": "高陵",
  "https://jiayuguan.esf.fang.com": "嘉峪关",
  "https://jinchang.esf.fang.com": "金昌",
  "https://baiyin.esf.fang.com": "白银",
  "https://tianshui.esf.fang.com": "天水",
  "https://wuwei.esf.fang.com": "武威",
  "https://zhangye.esf.fang.com": "张掖",
  "https://pingliang.esf.fang.com": "平凉",
  "https://jiuquan.esf.fang.com": "酒泉",
  "https://dingxi.esf.fang.com": "定西",
  "https://longnan.esf.fang.com": "陇南",
  "https://gannan.esf.fang.com": "甘南",
  "https://linxia.esf.fang.com": "临夏",
  "https://lz.esf.fang.com": "兰州",
  "https://qingyang.esf.fang.com": "庆阳",
  "https://yongdeng.esf.fang.com": "永登",
  "https://yuzhong.esf.fang.com": "榆中",
  "https://shizuishan.esf.fang.com": "石嘴山",
  "https://wuzhong.esf.fang.com": "吴忠",
  "https://guyuan.esf.fang.com": "固原",
  "https://zhongwei.esf.fang.com": "中卫",
  "https://yinchuan.esf.fang.com": "银川",
  "https://yushu.esf.fang.com": "玉树",
  "https://guoluo.esf.fang.com": "果洛",
  "https://huangnan.esf.fang.com": "黄南",
  "https://haixi.esf.fang.com": "海西",
  "https://haidong.esf.fang.com": "海东",
  "https://haibei.esf.fang.com": "海北",
  "https://xn.esf.fang.com": "西宁",
  "https://kelamayi.esf.fang.com": "克拉玛依",
  "https://alaer.esf.fang.com": "阿拉尔",
  "https://betl.esf.fang.com": "博尔塔拉",
  "https://tulufan.esf.fang.com": "吐鲁番",
  "https://kashi.esf.fang.com": "喀什",
  "https://tmsk.esf.fang.com": "图木舒克",
  "https://wujiaqu.esf.fang.com": "五家渠",
  "https://hami.esf.fang.com": "哈密",
  "https://hetian.esf.fang.com": "和田",
  "https://kuerle.esf.fang.com": "库尔勒",
  "https://kzls.esf.fang.com": "克孜勒苏",
  "https://akesu.esf.fang.com": "阿克苏",
  "https://bazhou.esf.fang.com": "巴州",
  "https://changji.esf.fang.com": "昌吉",
  "https://shihezi.esf.fang.com": "石河子",
  "https://xj.esf.fang.com": "乌鲁木齐",
  "https://yili.esf.fang.com": "伊犁",
  "https://kuitun.esf.fang.com": "奎屯",
  "https:https://hk.esf.fang.com/": "香港",
  "https:https://esf.macau.fang.com/": "澳门",
  "https:https://www.twproperty.com.tw/": "台湾"
}