{"北京": {"北京": "https://beijing.anjuke.com/"}, "天津": {"天津": "https://tianjin.anjuke.com/"}, "上海": {"上海": "https://shanghai.anjuke.com/"}, "重庆": {"重庆": "https://chongqing.anjuke.com/"}, "河北": {"石家庄": "https://sjz.anjuke.com/", "唐山": "https://tangshan.anjuke.com/", "秦皇岛": "https://qinhuangdao.anjuke.com/", "邯郸": "https://handan.anjuke.com/", "邢台": "https://xingtai.anjuke.com/", "保定": "https://baoding.anjuke.com/", "张家口": "https://zhangjiakou.anjuke.com/", "承德": "https://chengde.anjuke.com/", "沧州": "https://cangzhou.anjuke.com/", "廊坊": "https://langfang.anjuke.com/", "衡水": "https://hengshui.anjuke.com/"}, "山西": {"太原": "https://ty.anjuke.com/", "大同": "https://datong.anjuke.com/", "阳泉": "https://yangquan.anjuke.com/", "长治": "https://changzhi.anjuke.com/", "晋城": "https://jincheng.anjuke.com/", "朔州": "https://shuozhou.anjuke.com/", "晋中": "https://jinzhong.anjuke.com/", "运城": "https://yuncheng.anjuke.com/", "忻州": "https://xinzhou.anjuke.com/", "临汾": "https://linfen.anjuke.com/", "吕梁": "https://lvliang.anjuke.com/"}, "辽宁": {"沈阳": "https://sy.anjuke.com/", "大连": "https://dalian.anjuke.com/", "鞍山": "https://anshan.anjuke.com/", "抚顺": "https://fushun.anjuke.com/", "本溪": "https://benxi.anjuke.com/", "丹东": "https://dandong.anjuke.com/", "锦州": "https://jinzhou.anjuke.com/", "营口": "https://yingkou.anjuke.com/", "阜新": "https://fuxin.anjuke.com/", "辽阳": "https://liaoyang.anjuke.com/", "盘锦": "https://panjin.anjuke.com/", "铁岭": "https://tieling.anjuke.com/", "朝阳": "https://chaoyang.anjuke.com/", "葫芦岛": "https://huludao.anjuke.com/"}, "吉林": {"长春": "https://cc.anjuke.com/", "吉林": "https://jilin.anjuke.com/", "四平": "https://siping.anjuke.com/", "辽源": "https://liaoyuan.anjuke.com/", "通化": "https://tonghua.anjuke.com/", "白山": "https://baishan.anjuke.com/", "松原": "https://songyuan.anjuke.com/", "白城": "https://baicheng.anjuke.com/", "延边朝": 0}, "黑龙江": {"哈尔滨": "https://heb.anjuke.com/", "齐齐哈尔": "https://qiqihaer.anjuke.com/", "鸡西": "https://jixi.anjuke.com/", "鹤岗": "https://hegang.anjuke.com/", "双鸭山": "https://shuangyashan.anjuke.com/", "大庆": "https://daqing.anjuke.com/", "伊春": "https://yichunshi.anjuke.com/", "佳木斯": "https://jiamusi.anjuke.com/", "七台河": "https://qitaihe.anjuke.com/", "牡丹江": "https://mudanjiang.anjuke.com/", "黑河": "https://heihe.anjuke.com/", "绥化": "https://suihua.anjuke.com/"}, "江苏": {"南京": "https://nanjing.anjuke.com/", "无锡": "https://wuxi.anjuke.com/", "徐州": "https://xuzhou.anjuke.com/", "常州": "https://cz.anjuke.com/", "苏州": "https://suzhou.anjuke.com/", "南通": "https://nantong.anjuke.com/", "连云港": "https://lianyungang.anjuke.com/", "淮安": "https://huaian.anjuke.com/", "盐城": "https://yancheng.anjuke.com/", "扬州": "https://yangzhou.anjuke.com/", "镇江": "https://zhenjiang.anjuke.com/", "泰州": "https://taizhou.anjuke.com/", "宿迁": "https://suqian.anjuke.com/"}, "浙江": {"杭州": "https://hangzhou.anjuke.com/", "宁波": "https://nb.anjuke.com/", "温州": "https://wenzhou.anjuke.com/", "嘉兴": "https://jx.anjuke.com/", "湖州": "https://huzhou.anjuke.com/", "绍兴": "https://shaoxing.anjuke.com/", "金华": "https://jinhua.anjuke.com/", "衢州": "https://quzhou.anjuke.com/", "舟山": "https://zhoushan.anjuke.com/", "台州": "https://taiz.anjuke.com/", "丽水": "https://lishui.anjuke.com/"}, "安徽": {"合肥": "https://hf.anjuke.com/", "芜湖": "https://wuhu.anjuke.com/", "蚌埠": "https://bengbu.anjuke.com/", "淮南": "https://huainan.anjuke.com/", "马鞍山": "https://maanshan.anjuke.com/", "淮北": "https://huaibei.anjuke.com/", "铜陵": "https://tongling.anjuke.com/", "安庆": "https://anqing.anjuke.com/", "黄山": "https://huangshan.anjuke.com/", "滁州": "https://chuzhou.anjuke.com/", "阜阳": "https://fuyang.anjuke.com/", "宿州": "https://suzhoushi.anjuke.com/", "六安": "https://luan.anjuke.com/", "亳州": "https://bozhou.anjuke.com/", "池州": "https://chizhou.anjuke.com/", "宣城": "https://xuancheng.anjuke.com/"}, "福建": {"福州": "https://fz.anjuke.com/", "厦门": "https://xm.anjuke.com/", "莆田": "https://putian.anjuke.com/", "三明": "https://sanming.anjuke.com/", "泉州": "https://quanzhou.anjuke.com/", "漳州": "https://zhangzhou.anjuke.com/", "南平": "https://nanping.anjuke.com/", "龙岩": "https://longyan.anjuke.com/", "宁德": "https://ningde.anjuke.com/"}, "江西": {"南昌": "https://nc.anjuke.com/", "景德镇": "https://jingdezhen.anjuke.com/", "萍乡": "https://pingxiang.anjuke.com/", "九江": "https://jiujiang.anjuke.com/", "新余": "https://xinyu.anjuke.com/", "鹰潭": "https://yingtan.anjuke.com/", "赣州": "https://ganzhou.anjuke.com/", "吉安": "https://jian.anjuke.com/", "宜春": "https://yichun.anjuke.com/", "抚州": "https://fuzhoushi.anjuke.com/", "上饶": "https://shangrao.anjuke.com/"}, "山东": {"济南": "https://jinan.anjuke.com/", "青岛": "https://qd.anjuke.com/", "淄博": "https://zibo.anjuke.com/", "枣庄": "https://zaozhuang.anjuke.com/", "东营": "https://dongying.anjuke.com/", "烟台": "https://yt.anjuke.com/", "潍坊": "https://weifang.anjuke.com/", "济宁": "https://jining.anjuke.com/", "泰安": "https://taian.anjuke.com/", "威海": "https://weihai.anjuke.com/", "日照": "https://rizhao.anjuke.com/", "临沂": "https://linyi.anjuke.com/", "德州": "https://dezhou.anjuke.com/", "聊城": "https://liaocheng.anjuke.com/", "滨州": "https://binzhou.anjuke.com/", "菏泽": "https://heze.anjuke.com/"}, "河南": {"郑州": "https://zhengzhou.anjuke.com/", "开封": "https://kaifeng.anjuke.com/", "洛阳": "https://luoyang.anjuke.com/", "平顶山": "https://pingdingsha.anjuke.com/", "安阳": "https://anyang.anjuke.com/", "鹤壁": "https://hebi.anjuke.com/", "新乡": "https://xinxiang.anjuke.com/", "焦作": "https://jiaozuo.anjuke.com/", "濮阳": "https://puyang.anjuke.com/", "许昌": "https://xuchang.anjuke.com/", "漯河": "https://luohe.anjuke.com/", "三门峡": "https://sanmenxia.anjuke.com/", "南阳": "https://nanyang.anjuke.com/", "商丘": "https://shangqiu.anjuke.com/", "信阳": "https://xinyang.anjuke.com/", "周口": "https://zhoukou.anjuke.com/", "驻马店": "https://zhumadian.anjuke.com/", "济源": "https://jiyuan.anjuke.com/"}, "湖北": {"武汉": "https://wuhan.anjuke.com/", "黄石": "https://huangshi.anjuke.com/", "十堰": "https://shiyan.anjuke.com/", "宜昌": "https://yichang.anjuke.com/", "襄阳": "https://xiangyang.anjuke.com/", "鄂州": "https://ezhou.anjuke.com/", "荆门": "https://jingmen.anjuke.com/", "孝感": "https://xiaogan.anjuke.com/", "荆州": "https://jingzhou.anjuke.com/", "黄冈": "https://huanggang.anjuke.com/", "咸宁": "https://xianning.anjuke.com/", "随州": "https://suizhou.anjuke.com/", "潜江": "https://qianjiang.anjuke.com/", "天门": "https://tianmen.anjuke.com/", "仙桃": "https://xiantao.anjuke.com/"}, "湖南": {"长沙": "https://cs.anjuke.com/", "株洲": "https://zhuzhou.anjuke.com/", "湘潭": "https://xiangtan.anjuke.com/", "衡阳": "https://hengyang.anjuke.com/", "邵阳": "https://shaoyang.anjuke.com/", "岳阳": "https://yueyang.anjuke.com/", "常德": "https://changde.anjuke.com/", "张家界": "https://zhangjiajie.anjuke.com/", "益阳": "https://yiyang.anjuke.com/", "郴州": "https://chenzhou.anjuke.com/", "永州": "https://yongzhou.anjuke.com/", "怀化": "https://huaihua.anjuke.com/", "娄底": "https://loudi.anjuke.com/"}, "广东": {"广州": "https://guangzhou.anjuke.com/", "韶关": "https://shaoguan.anjuke.com/", "深圳": "https://shenzhen.anjuke.com/", "珠海": "https://zh.anjuke.com/", "汕头": "https://shantou.anjuke.com/", "佛山": "https://foshan.anjuke.com/", "江门": "https://jiangmen.anjuke.com/", "湛江": "https://zhanjiang.anjuke.com/", "茂名": "https://maoming.anjuke.com/", "肇庆": "https://zhaoqing.anjuke.com/", "惠州": "https://huizhou.anjuke.com/", "梅州": "https://meizhou.anjuke.com/", "汕尾": "https://shanwei.anjuke.com/", "河源": "https://heyuan.anjuke.com/", "阳江": "https://yangjiang.anjuke.com/", "清远": "https://qingyuan.anjuke.com/", "东莞": "https://dg.anjuke.com/", "中山": "https://zs.anjuke.com/", "潮州": "https://chaozhou.anjuke.com/", "揭阳": "https://jieyang.anjuke.com/", "云浮": "https://yufu.anjuke.com/"}, "广西": {"南宁": "https://nanning.anjuke.com/", "柳州": "https://liuzhou.anjuke.com/", "桂林": "https://guilin.anjuke.com/", "梧州": "https://wuzhou.anjuke.com/", "北海": "https://beihai.anjuke.com/", "防城港": "https://fangchenggang.anjuke.com/", "钦州": "https://qinzhou.anjuke.com/", "贵港": "https://guigang.anjuke.com/", "玉林": "https://yulinshi.anjuke.com/", "百色": "https://baise.anjuke.com/", "贺州": "https://hezhou.anjuke.com/", "河池": "https://hechi.anjuke.com/", "来宾": "https://laibin.anjuke.com/", "崇左": "https://chongzuo.anjuke.com/"}, "海南": {"海口": "https://haikou.anjuke.com/", "三亚": "https://sanya.anjuke.com/", "三沙": "https://sansha.anjuke.com/", "儋州": "https://danzhou.anjuke.com/"}, "四川": {"成都": "https://chengdu.anjuke.com/", "自贡": "https://zigong.anjuke.com/", "攀枝花": "https://panzhihua.anjuke.com/", "泸州": "https://luzhou.anjuke.com/", "德阳": "https://deyang.anjuke.com/", "绵阳": "https://mianyang.anjuke.com/", "广元": "https://guangyuan.anjuke.com/", "遂宁": "https://suining.anjuke.com/", "内江": "https://neijiang.anjuke.com/", "乐山": "https://leshan.anjuke.com/", "南充": "https://nanchong.anjuke.com/", "眉山": "https://meishan.anjuke.com/", "宜宾": "https://yibin.anjuke.com/", "广安": "https://guangan.anjuke.com/", "达州": "https://dazhou.anjuke.com/", "雅安": "https://yaan.anjuke.com/", "巴中": "https://bazhong.anjuke.com/", "资阳": "https://ziyang.anjuke.com/", "甘孜": "https://ganzi.anjuke.com/", "凉山": "https://liangshan.anjuke.com/"}, "贵州": {"贵阳": "https://gy.anjuke.com/", "六盘水": "https://liupanshui.anjuke.com/", "遵义": "https://zunyi.anjuke.com/", "安顺": "https://anshun.anjuke.com/", "毕节": "https://bijie.anjuke.com/", "铜仁": "https://tongren.anjuke.com/", "黔西南": "https://qianxinan.anjuke.com/", "黔东南": "https://qiandongnan.anjuke.com/", "黔南": "https://qiannan.anjuke.com/"}, "云南": {"昆明": "https://km.anjuke.com/", "曲靖": "https://qujing.anjuke.com/", "玉溪": "https://yuxi.anjuke.com/", "保山": "https://baoshan.anjuke.com/", "昭通": "https://zhaotong.anjuke.com/", "丽江": "https://lijiang.anjuke.com/", "普洱": "https://puer.anjuke.com/", "临沧": "https://lingcang.anjuke.com/", "楚雄": "https://chuxiong.anjuke.com/", "红河": "https://honghe.anjuke.com/", "文山": "https://wenshan.anjuke.com/", "西双版纳": "https://bannan.anjuke.com/", "大理": "https://dali.anjuke.com/", "迪庆": "https://diqing.anjuke.com/"}, "西藏": {"拉萨": "https://lasa.anjuke.com/", "昌都": "https://changdu.anjuke.com/", "山南": "https://shannan.anjuke.com/", "日喀则": "https://rikeze.anjuke.com/", "那曲": "https://naqu.anjuke.com/", "林芝": "https://linzhi.anjuke.com/"}, "陕西": {"西安": "https://xa.anjuke.com/", "铜川": "https://tongchuan.anjuke.com/", "宝鸡": "https://baoji.anjuke.com/", "咸阳": "https://xianyang.anjuke.com/", "渭南": "https://weinan.anjuke.com/", "延安": "https://yanan.anjuke.com/", "汉中": "https://hanzhong.anjuke.com/", "榆林": "https://yulin.anjuke.com/", "安康": "https://ankang.anjuke.com/", "商洛": "https://shangluo.anjuke.com/"}, "甘肃": {"兰州": "https://lanzhou.anjuke.com/", "嘉峪关": "https://jiayuguan.anjuke.com/", "金昌": "https://jinchang.anjuke.com/", "白银": "https://baiyin.anjuke.com/", "天水": "https://tianshui.anjuke.com/", "酒泉": "https://jiuquan.anjuke.com/", "张掖": "https://zhangye.anjuke.com/", "武威": "https://wuwei.anjuke.com/", "定西": "https://dingxi.anjuke.com/", "陇南": "https://longnan.anjuke.com/", "平凉": "https://pingliang.anjuke.com/", "庆阳": "https://qingyang.anjuke.com/", "临夏": "https://linxia.anjuke.com/", "甘南": "https://gannan.anjuke.com/"}, "青海": {"西宁": "https://xining.anjuke.com/", "海东": "https://haidong.anjuke.com/", "海北": "https://haibei.anjuke.com/", "黄南": "https://huangnan.anjuke.com/", "海南": "https://hainan.anjuke.com/", "果洛": "https://guoluo.anjuke.com/", "玉树": "https://yushu.anjuke.com/"}, "宁夏": {"银川": "https://yinchuan.anjuke.com/", "石嘴山": "https://shizuishan.anjuke.com/", "吴忠": "https://wuzhong.anjuke.com/", "固原": "https://guyuan.anjuke.com/", "中卫": "https://weizhong.anjuke.com/"}, "新疆": {"乌鲁木齐": "https://wulumuqi.anjuke.com/", "克拉玛依": "https://kelamayi.anjuke.com/", "吐鲁番": "https://tulufan.anjuke.com/", "哈密": "https://hami.anjuke.com/", "昌吉": "https://changji.anjuke.com/", "博尔塔拉": "https://boertala.anjuke.com/", "巴音郭楞": "https://bayinguoleng.anjuke.com/" , "石河子": "https://shihezi.anjuke.com/", "阿拉尔": "https://alaer.anjuke.com/", "图木舒克": "https://tumushuke.anjuke.com/", "五家渠": "https://wujiaqu.anjuke.com/", "胡杨河": "https://huyanghe.anjuke.com/", "可克达拉": "https://kekedala.anjuke.com/"}, "内蒙古": {"呼和浩特": "https://huhehaote.anjuke.com/", "包头": "https://baotou.anjuke.com/", "乌海": "https://wuhai.anjuke.com/", "赤峰": "https://chifeng.anjuke.com/", "通辽": "https://tongliao.anjuke.com/", "鄂尔多斯": "https://eerduosi.anjuke.com/", "呼伦贝尔": "https://hulunbeier.anjuke.com/", "巴彦淖尔": 0, "乌兰察布": "https://wulanchabu.anjuke.com/", "兴安盟": "https://xinganmeng.anjuke.com/", "锡林郭勒盟": 0, "阿拉善盟": "https://alashanm.anjuke.com/"}, "香港特别行政区": {"中国香港": "https://hk.fang.anjuke.com/"}}
